[
  {
    "route": "/staff",
    "firstLoadUncompressedJsBytes": 540249,
    "firstLoadChunkPaths": [
      ".next\\static\\chunks\\2q1swlgb_gdyl.js",
      ".next\\static\\chunks\\1xfm2zh1welgm.js",
      ".next\\static\\chunks\\1zzlri0ra42-2.js",
      ".next\\static\\chunks\\1joenc9d730iw.js",
      ".next\\static\\chunks\\419k60_dmf0bw.js",
      ".next\\static\\chunks\\0z0jn-k3a04vs.js",
      ".next\\static\\chunks\\28ssk53zrsfsk.js",
      ".next\\static\\chunks\\turbopack-2mpqludk75jex.js"
    ]
  },
  {
    "route": "/room/[roomId]",
    "firstLoadUncompressedJsBytes": 534700,
    "firstLoadChunkPaths": [
      ".next\\static\\chunks\\2q1swlgb_gdyl.js",
      ".next\\static\\chunks\\1xfm2zh1welgm.js",
      ".next\\static\\chunks\\35xea3el_ps_n.js",
      ".next\\static\\chunks\\1joenc9d730iw.js",
      ".next\\static\\chunks\\419k60_dmf0bw.js",
      ".next\\static\\chunks\\0z0jn-k3a04vs.js",
      ".next\\static\\chunks\\28ssk53zrsfsk.js",
      ".next\\static\\chunks\\turbopack-2mpqludk75jex.js"
    ]
  },
  {
    "route": "/",
    "firstLoadUncompressedJsBytes": 527616,
    "firstLoadChunkPaths": [
      ".next\\static\\chunks\\2q1swlgb_gdyl.js",
      ".next\\static\\chunks\\1xfm2zh1welgm.js",
      ".next\\static\\chunks\\1---losni2fh4.js",
      ".next\\static\\chunks\\1joenc9d730iw.js",
      ".next\\static\\chunks\\419k60_dmf0bw.js",
      ".next\\static\\chunks\\0z0jn-k3a04vs.js",
      ".next\\static\\chunks\\28ssk53zrsfsk.js",
      ".next\\static\\chunks\\turbopack-2mpqludk75jex.js"
    ]
  },
  {
    "route": "/_not-found",
    "firstLoadUncompressedJsBytes": 514672,
    "firstLoadChunkPaths": [
      ".next\\static\\chunks\\2q1swlgb_gdyl.js",
      ".next\\static\\chunks\\1xfm2zh1welgm.js",
      ".next\\static\\chunks\\1joenc9d730iw.js",
      ".next\\static\\chunks\\419k60_dmf0bw.js",
      ".next\\static\\chunks\\0z0jn-k3a04vs.js",
      ".next\\static\\chunks\\28ssk53zrsfsk.js",
      ".next\\static\\chunks\\turbopack-2mpqludk75jex.js"
    ]
  }
]